setup.py
gabmap/__init__.py
gabmap.egg-info/PKG-INFO
gabmap.egg-info/SOURCES.txt
gabmap.egg-info/dependency_links.txt
gabmap.egg-info/requires.txt
gabmap.egg-info/top_level.txt
gabmap.egg-info/zip-safe